ssm_tree/__init__.py
ssm_tree/__main__.py
ssm_tree/main.py
aws_ssm_tree-0.2.1.dist-info/LICENSE
aws_ssm_tree-0.2.1.dist-info/METADATA
aws_ssm_tree-0.2.1.dist-info/WHEEL
aws_ssm_tree-0.2.1.dist-info/entry_points.txt
aws_ssm_tree-0.2.1.dist-info/top_level.txt
aws_ssm_tree-0.2.1.dist-info/RECORD
