Metadata-Version: 2.1
Name: aws-ssm-tree
Version: 0.2.1
Summary: Builds a tree of parameters from AWS System Manager Parameter Store.
Home-page: https://github.com/brunorubin/aws-ssm-tree
Author: Bruno Rubin
Author-email: bruno.rubin@gmail.com
License: UNKNOWN
Platform: UNKNOWN
Classifier: Programming Language :: Python :: 3
Classifier: License :: OSI Approved :: MIT License
Classifier: Operating System :: OS Independent
Requires-Dist: click
Requires-Dist: boto3
Requires-Dist: treelib
